markdownx/__init__.py
markdownx/admin.py
markdownx/exceptions.py
markdownx/fields.py
markdownx/forms.py
markdownx/models.py
markdownx/settings.py
markdownx/urls.py
markdownx/utils.py
markdownx/views.py
markdownx/widgets.py
markdownx/locale/de/LC_MESSAGES/django.mo
markdownx/locale/de/LC_MESSAGES/django.po
markdownx/locale/du/LC_MESSAGES/django.mo
markdownx/locale/du/LC_MESSAGES/django.po
markdownx/locale/en/LC_MESSAGES/django.mo
markdownx/locale/en/LC_MESSAGES/django.po
markdownx/locale/fa/LC_MESSAGES/django.po
markdownx/locale/fr/LC_MESSAGES/django.mo
markdownx/locale/fr/LC_MESSAGES/django.po
markdownx/locale/pl/LC_MESSAGES/django.mo
markdownx/locale/pl/LC_MESSAGES/django.po
markdownx/static/markdownx/admin/css/markdownx.css
markdownx/static/markdownx/admin/css/markdownx.min.css
markdownx/static/markdownx/js/markdownx.js
markdownx/static/markdownx/js/markdownx.min.js
markdownx/templates/markdownx/widget.html
markdownx/tests/__init__.py
markdownx/tests/models.py
markdownx/tests/tests.py
markdownx/tests/urls.py
markdownx/tests/views.py
markdownx/tests/static/django-markdownx-preview.png
markdownx/tests/templates/test_view.html
django_markdownx-4.0.9.dist-info/LICENSE
django_markdownx-4.0.9.dist-info/METADATA
django_markdownx-4.0.9.dist-info/WHEEL
django_markdownx-4.0.9.dist-info/top_level.txt
django_markdownx-4.0.9.dist-info/RECORD
