Metadata-Version: 2.1
Name: django-markdownx
Version: 4.0.9
Summary: A comprehensive Markdown editor built for Django.
Home-page: https://github.com/neutronX/django-markdownx
Maintainer: Adi, Pouria Hadjibagheri
License: BSD
Keywords: django markdown markdownx django-markdownx editor image upload drag&drop ajax
Classifier: Development Status :: 5 - Production/Stable
Classifier: Environment :: Web Environment
Classifier: Environment :: Plugins
Classifier: Framework :: Django
Classifier: Intended Audience :: Developers
Classifier: License :: OSI Approved :: BSD License
Classifier: Operating System :: OS Independent
Classifier: Programming Language :: Python
Classifier: Programming Language :: JavaScript
Classifier: Topic :: Software Development :: Libraries :: Python Modules
Classifier: Topic :: Multimedia :: Graphics
Classifier: Topic :: Text Processing :: Markup
Classifier: Topic :: Text Editors :: Text Processing
Classifier: Topic :: Text Editors :: Word Processors
Classifier: Topic :: Text Processing :: Markup :: HTML
Classifier: Topic :: Multimedia :: Graphics :: Presentation
Classifier: Topic :: Internet :: WWW/HTTP
Classifier: Topic :: Internet :: WWW/HTTP :: Site Management
License-File: LICENSE
